cogdata/__init__.py
cogdata/arguments.py
cogdata/cli.py
cogdata/data_manager.py
cogdata/data_processor.py
cogdata/process_single_entry.py
cogdata/version.py
cogdata/data_savers/__init__.py
cogdata/data_savers/base_saver.py
cogdata/data_savers/binary_saver.py
cogdata/data_savers/tar_saver.py
cogdata/datasets/__init__.py
cogdata/datasets/binary_dataset.py
cogdata/datasets/rar_dataset.py
cogdata/datasets/tar_dataset.py
cogdata/datasets/txt_dataset.py
cogdata/datasets/zip_dataset.py
cogdata/tasks/__init__.py
cogdata/tasks/base_task.py
cogdata/tasks/icetk_image_text_task.py
cogdata/tasks/icetk_text_task.py
cogdata/tasks/image_text_tokenization_task.py
cogdata/utils/__init__.py
cogdata/utils/eprogress.py
cogdata/utils/helpers.py
cogdata/utils/logger.py
cogdata/utils/progress_record.py
cogdata/utils/register.py
cogdata/utils/cogview/__init__.py
cogdata/utils/cogview/api.py
cogdata/utils/cogview/sp_tokenizer.py
cogdata/utils/cogview/unified_tokenizer.py
cogdata/utils/cogview/vqvae_tokenizer.py
cogdata/utils/cogview/vqvae_zc.py
cogdata/utils/cogview/chinese_sentencepiece/cog-pretrain.model
cogdata-0.0.7.data/scripts/install_unrarlib.sh
cogdata-0.0.7.dist-info/LICENSE
cogdata-0.0.7.dist-info/METADATA
cogdata-0.0.7.dist-info/WHEEL
cogdata-0.0.7.dist-info/entry_points.txt
cogdata-0.0.7.dist-info/top_level.txt
cogdata-0.0.7.dist-info/RECORD
