Metadata-Version: 2.1
Name: cogdata
Version: 0.0.7
Summary: A lightweight data management and preprocessing tool.
Home-page: https://github.com/Sleepychord/cogdata
Author: Ming Ding, Yuxiang Chen, Wendi Zheng
Author-email: dm_thu@qq.com
License: MIT license
Platform: UNKNOWN
Requires-Python: >=3.5
License-File: LICENSE
Requires-Dist: numpy
Requires-Dist: torch
Requires-Dist: pytest
Requires-Dist: unrar
Requires-Dist: tqdm
Requires-Dist: icetk
